CustomXMLParser/__init__.py
CustomXMLParser/main.py
CustomXMLParser/version.py
CustomXMLParser-1.1.1.dist-info/LICENSE
CustomXMLParser-1.1.1.dist-info/METADATA
CustomXMLParser-1.1.1.dist-info/WHEEL
CustomXMLParser-1.1.1.dist-info/top_level.txt
CustomXMLParser-1.1.1.dist-info/RECORD
