Metadata-Version: 2.1
Name: CustomXMLParser
Version: 1.1.1
Summary: Python Libary that allows for customized parsing of XML files using a set of configurations. Output is a dictonary. This library builds on the xml2dict library.
Home-page: https://github.com/mhamdan91/CustomXMLParser
Author: mhamdan91 (Hamdan, Muhammad)
Author-email: <mhamdan.dev@gmail.com>
Keywords: python,xml,XML,parsing,mapping,dictionary,configurable,custom,formatting
Classifier: Development Status :: 5 - Production/Stable
Classifier: Intended Audience :: Developers
Classifier: Programming Language :: Python :: 3
Classifier: Operating System :: Unix
Classifier: Operating System :: MacOS :: MacOS X
Classifier: Operating System :: Microsoft :: Windows
Classifier: License :: OSI Approved :: BSD License
License-File: LICENSE
Requires-Dist: xmltodict ==0.13.0
Requires-Dist: moecolor
